mcsas3/McSAS.code-workspace
mcsas3/__init__.py
mcsas3/__main__.py
mcsas3/cli_tools.py
mcsas3/mc_analysis.py
mcsas3/mc_core.py
mcsas3/mc_data.py
mcsas3/mc_data_1d.py
mcsas3/mc_data_2d.py
mcsas3/mc_hat.py
mcsas3/mc_hdf.py
mcsas3/mc_model.py
mcsas3/mc_model_histogrammer.py
mcsas3/mc_opt.py
mcsas3/mc_plot.py
mcsas3/mcsas3_cli_histogrammer.py
mcsas3/mcsas3_cli_runner.py
mcsas3/osb.py
mcsas3-1.0.6.dist-info/licenses/AUTHORS.rst
mcsas3-1.0.6.dist-info/licenses/LICENSE
mcsas3-1.0.6.dist-info/METADATA
mcsas3-1.0.6.dist-info/WHEEL
mcsas3-1.0.6.dist-info/entry_points.txt
mcsas3-1.0.6.dist-info/top_level.txt
mcsas3-1.0.6.dist-info/RECORD
