Metadata-Version: 2.4
Name: mcsas3
Version: 1.0.6
Summary: A refactored McSAS for analysis of X-ray and Neutron scattering data.
Author-email: "Brian R. Pauw" <brian.pauw@bam.de>, Ingo Breßler <ingo.bressler@bam.de>
License-Expression: GPL-3.0-or-later
Project-URL: homepage, https://BAMresearch.github.io/McSAS3
Project-URL: documentation, https://BAMresearch.github.io/McSAS3
Project-URL: repository, https://github.com/BAMresearch/McSAS3
Project-URL: changelog, https://BAMresearch.github.io/McSAS3/changelog.html
Classifier: Development Status :: 4 - Beta
Classifier: Operating System :: Unix
Classifier: Operating System :: POSIX
Classifier: Operating System :: MacOS
Classifier: Operating System :: Microsoft :: Windows
Classifier: Programming Language :: Python
Classifier: Programming Language :: Python :: 3
Classifier: Programming Language :: Python :: 3 :: Only
Classifier: Programming Language :: Python :: 3.11
Classifier: Programming Language :: Python :: 3.12
Classifier: Programming Language :: Python :: 3.13
Classifier: Programming Language :: Python :: Implementation :: CPython
Classifier: Framework :: Jupyter :: JupyterLab
Classifier: Topic :: Utilities
Classifier: Topic :: Scientific/Engineering
Classifier: Intended Audience :: Developers
Classifier: Intended Audience :: Science/Research
License-File: LICENSE
License-File: AUTHORS.rst
Requires-Dist: pyyaml
Requires-Dist: pandas
Requires-Dist: attrs
Requires-Dist: h5py
Requires-Dist: pint
Requires-Dist: sasmodels
Dynamic: license-file
